SureTypeSC/Config.py
SureTypeSC/DataLoader.py
SureTypeSC/MachineLearning.py
SureTypeSC/Settings.py
SureTypeSC/Timer.py
SureTypeSC/Transformations.py
SureTypeSC/__init__.py
SureTypeSC/classifier.py
SureTypeSC/genome_library.py
SureTypeSC/protocol.py
SureTypeSC-1.1.0.dist-info/METADATA
SureTypeSC-1.1.0.dist-info/WHEEL
SureTypeSC-1.1.0.dist-info/top_level.txt
SureTypeSC-1.1.0.dist-info/RECORD
