Metadata-Version: 2.1
Name: SureTypeSC
Version: 1.1.0
Summary: SureTypeSC - software for improved genotyping in the single cell environment
Home-page: https://github.com/puko818/SureTypeSC
Author: Ivan Vogel
Author-email: ivogel@sund.ku.dk
License: MIT
Platform: UNKNOWN
Classifier: License :: OSI Approved :: MIT License
Classifier: Programming Language :: Python
Classifier: Programming Language :: Python :: 3
Classifier: Programming Language :: Python :: 3.6
Classifier: Programming Language :: Python :: Implementation :: CPython
Classifier: Programming Language :: Python :: Implementation :: PyPy
Requires-Python: >=3
Requires-Dist: pandas
Requires-Dist: sklearn
Requires-Dist: scikit-learn
Requires-Dist: numpy
Requires-Dist: IlluminaBeadArrayFiles
Requires-Dist: python-docx
Requires-Dist: tabulate
Requires-Dist: json-tricks
